DownloadDMARCFilesFromGmail/GmailAuth.py
DownloadDMARCFilesFromGmail/GmailLabelQuery.py
DownloadDMARCFilesFromGmail/__init__.py
DownloadDMARCFilesFromGmail/__main__.py
DownloadDMARCFilesFromGmail/download.py
DownloadDMARCAttachmentsFromGmail-0.2.0.dist-info/LICENSE
DownloadDMARCAttachmentsFromGmail-0.2.0.dist-info/METADATA
DownloadDMARCAttachmentsFromGmail-0.2.0.dist-info/WHEEL
DownloadDMARCAttachmentsFromGmail-0.2.0.dist-info/entry_points.txt
DownloadDMARCAttachmentsFromGmail-0.2.0.dist-info/top_level.txt
DownloadDMARCAttachmentsFromGmail-0.2.0.dist-info/RECORD
