Metadata-Version: 2.1
Name: DownloadDMARCAttachmentsFromGmail
Version: 0.2.0
Summary: Downloads DMARC attachments from Gmail
Home-page: https://github.com/MozaicWorks/DownloadDMARCAttachmentsFromGmail
Author: Mozaic Works
Author-email: alex.bolboaca@mozaicworks.com
Project-URL: Bug Reports, https://github.com/MozaicWorks/DownloadDMARCAttachmentsFromGmail/issues
Project-URL: Source, https://github.com/MozaicWorks/DownloadDMARCAttachmentsFromGmail/
Keywords: DMARC Gmail
Classifier: Development Status :: 3 - Alpha
Classifier: Intended Audience :: Developers
Classifier: Topic :: Communications :: Email
Classifier: License :: OSI Approved :: MIT License
Classifier: Programming Language :: Python :: 3.10
Requires-Python: >=3.10
License-File: LICENSE
Requires-Dist: google-api-python-client (==2.77.0)
Requires-Dist: google-auth-httplib2 (==0.1.0)
Requires-Dist: google-auth-oauthlib (==1.0.0)
Requires-Dist: pyasn1 (==0.4.8)
Requires-Dist: pyasn1-modules (==0.2.8)
Requires-Dist: httplib2 (==0.21.0) ; python_version >= "2.7" and python_version not in "3.0, 3.1, 3.2, 3.3"
Requires-Dist: requests-oauthlib (==1.3.1) ; python_version >= "2.7" and python_version not in "3.0, 3.1, 3.2, 3.3"
Requires-Dist: six (==1.16.0) ; python_version >= "2.7" and python_version not in "3.0, 3.1, 3.2, 3.3"
Requires-Dist: google-auth (==2.16.0) ; python_version >= "2.7" and python_version not in "3.0, 3.1, 3.2, 3.3, 3.4, 3.5"
Requires-Dist: urllib3 (==1.26.14) ; python_version >= "2.7" and python_version not in "3.0, 3.1, 3.2, 3.3, 3.4, 3.5"
Requires-Dist: pyparsing (==3.0.9) ; python_version >= "3.1"
Requires-Dist: idna (==3.4) ; python_version >= "3.5"
Requires-Dist: certifi (==2022.12.7) ; python_version >= "3.6"
Requires-Dist: charset-normalizer (==3.0.1) ; python_version >= "3.6"
Requires-Dist: oauthlib (==3.2.2) ; python_version >= "3.6"
Requires-Dist: rsa (==4.9) ; python_version >= "3.6"
Requires-Dist: uritemplate (==4.1.1) ; python_version >= "3.6"
Requires-Dist: google-api-core (==2.11.0) ; python_version >= "3.7"
Requires-Dist: googleapis-common-protos (==1.58.0) ; python_version >= "3.7"
Requires-Dist: protobuf (==4.21.12) ; python_version >= "3.7"
Requires-Dist: requests (==2.28.2) ; python_version >= "3.7" and python_version < "4"
Requires-Dist: cachetools (==5.3.0) ; python_version ~= "3.7"
Provides-Extra: dev
